gd_sofa_utils-0.0.2.dist-info/licenses/LICENSE
gdsofa/__init__.py
gdsofa/load_SOFA.py
gdsofa/sofa_parameters.py
gdsofa/sofawrap.py
gdsofa/utils.py
gdsofa/visual.py
gdsofa/comps/__init__.py
gdsofa/comps/_build_dynamic_lib.py
gdsofa/comps/_dyn.py
gdsofa/comps/base_component.py
gdsofa/controller/__init__.py
gdsofa/controller/controller.py
gdsofa/controller/controller_data.py
gdsofa/core/__init__.py
gdsofa/core/component.py
gdsofa/core/links.py
gdsofa/core/node.py
gd_sofa_utils-0.0.2.dist-info/METADATA
gd_sofa_utils-0.0.2.dist-info/WHEEL
gd_sofa_utils-0.0.2.dist-info/top_level.txt
gd_sofa_utils-0.0.2.dist-info/RECORD
