Metadata-Version: 2.4
Name: gd-sofa-utils
Version: 0.0.2
Requires-Python: ==3.12.*
License-File: LICENSE
Requires-Dist: gd-py-utils
Requires-Dist: randomname
Requires-Dist: colour
Requires-Dist: param
Requires-Dist: treelib
Requires-Dist: numpy
Requires-Dist: pandas
Provides-Extra: docs
Requires-Dist: mkdocs; extra == "docs"
Requires-Dist: mkdocs-material; extra == "docs"
Requires-Dist: mkdocs-mermaid2-plugin; extra == "docs"
Requires-Dist: mkdocs-snippets; extra == "docs"
Requires-Dist: mkdocs-exclude; extra == "docs"
Requires-Dist: mkdocstrings-python; extra == "docs"
Dynamic: license-file
